extension/__init__.py
testinnanda-0.1.1.dist-info/LICENSE.txt
testinnanda-0.1.1.dist-info/METADATA
testinnanda-0.1.1.dist-info/WHEEL
testinnanda-0.1.1.dist-info/top_level.txt
testinnanda-0.1.1.dist-info/RECORD
