Metadata-Version: 2.1
Name: testinnanda
Version: 0.1.1
Summary: nanda basic maths tools
Author: nanda
Author-email: nandagopalherballife@gmail.com
Classifier: Programming Language :: Python :: 3
Classifier: License :: OSI Approved :: MIT License
Classifier: Operating System :: OS Independent
License-File: LICENSE.txt
